LICENSE
MANIFEST.in
README.md
requirements.txt
setup.py
mutt_ics/__init__.py
mutt_ics/mutt_ics.py
mutt_ics.egg-info/PKG-INFO
mutt_ics.egg-info/SOURCES.txt
mutt_ics.egg-info/dependency_links.txt
mutt_ics.egg-info/entry_points.txt
mutt_ics.egg-info/not-zip-safe
mutt_ics.egg-info/requires.txt
mutt_ics.egg-info/top_level.txt
samples/1.ics
samples/2.ics
samples/3.ics
samples/4.ics
samples/5.ics