Metadata-Version: 1.1
Name: mutt-ics
Version: 0.9.2
Summary: A tool to show calendar event details in Mutt.
Home-page: https://github.com/dmedvinsky/mutt-ics
Author: Dmitry Medvinsky
Author-email: me@dmedvinsky.name
License: MIT
Keywords: ics calendar mutt
Platform: UNKNOWN
Classifier: Development Status :: 3 - Alpha
Classifier: License :: OSI Approved :: MIT License
